ofbahar_pdf_converter/__init__.py
ofbahar_pdf_converter/server.py
ofbahar_pdf_converter-0.1.1.dist-info/METADATA
ofbahar_pdf_converter-0.1.1.dist-info/WHEEL
ofbahar_pdf_converter-0.1.1.dist-info/entry_points.txt
ofbahar_pdf_converter-0.1.1.dist-info/RECORD
