Metadata-Version: 2.3
Name: ofbahar-pdf-converter
Version: 0.1.1
Summary: An MCP server that converts text to PDF and provides various PDF manipulation tools - developed by ofbahar
Author-email: ofbahar <ofbahar@hotmail.com>
Requires-Python: >=3.12
Requires-Dist: mcp>=1.1.0
Requires-Dist: pypdf2>=3.0.1
Requires-Dist: reportlab>=4.2.5
